{
  "main": {
    "id": "9ab42ed322798174",
    "type": "split",
    "children": [
      {
        "id": "6ca388d6df42d8a6",
        "type": "tabs",
        "children": [
          {
            "id": "8c6ae1f3578383a9",
            "type": "leaf",
            "state": {
              "type": "markdown",
              "state": {
                "file": "정보보호/Feistel Cipher.md",
                "mode": "source",
                "backlinks": false,
                "source": false
              }
            }
          },
          {
            "id": "8f50cdd95e2a933e",
            "type": "leaf",
            "state": {
              "type": "markdown",
              "state": {
                "file": "프로그래밍언어/고급 프로그래밍 언어.md",
                "mode": "source",
                "backlinks": false,
                "source": false
              }
            }
          },
          {
            "id": "2140c71f0e3321a8",
            "type": "leaf",
            "state": {
              "type": "markdown",
              "state": {
                "file": "프로그래밍언어/JavaScript(JS).md",
                "mode": "source",
                "backlinks": false,
                "source": false
              }
            }
          },
          {
            "id": "4e715e4826be128a",
            "type": "leaf",
            "state": {
              "type": "markdown",
              "state": {
                "file": "프로그래밍언어/Next.js.md",
                "mode": "source",
                "backlinks": false,
                "source": false
              }
            }
          }
        ],
        "currentTab": 3
      },
      {
        "id": "91708b97934ddb35",
        "type": "tabs",
        "children": [
          {
            "id": "02dec48cf6ebe13b",
            "type": "leaf",
            "state": {
              "type": "markdown",
              "state": {
                "file": "프로그래밍언어/React.js.md",
                "mode": "source",
                "backlinks": false,
                "source": false
              }
            }
          }
        ]
      }
    ],
    "direction": "vertical"
  },
  "left": {
    "id": "719b28e096d2c92a",
    "type": "split",
    "children": [
      {
        "id": "709e850799a9f562",
        "type": "tabs",
        "children": [
          {
            "id": "dc290b6402d54d9c",
            "type": "leaf",
            "state": {
              "type": "file-explorer",
              "state": {
                "sortOrder": "alphabetical"
              }
            }
          },
          {
            "id": "09bd65624b0416e2",
            "type": "leaf",
            "state": {
              "type": "mk-file-view",
              "state": {}
            }
          },
          {
            "id": "5285295c62f53e8e",
            "type": "leaf",
            "state": {
              "type": "search",
              "state": {
                "query": "",
                "matchingCase": false,
                "explainSearch": false,
                "collapseAll": false,
                "extraContext": false,
                "sortOrder": "alphabetical"
              }
            }
          }
        ]
      }
    ],
    "direction": "horizontal",
    "width": 217.5
  },
  "right": {
    "id": "fa8e5b36a88c24c1",
    "type": "split",
    "children": [
      {
        "id": "cb9ed115168abbac",
        "type": "tabs",
        "children": [
          {
            "id": "bccc5cc92cfd6777",
            "type": "leaf",
            "state": {
              "type": "outline",
              "state": {
                "file": "프로그래밍언어/Next.js.md"
              }
            }
          },
          {
            "id": "b3f5e02c69cae736",
            "type": "leaf",
            "state": {
              "type": "outgoing-link",
              "state": {
                "file": "프로그래밍언어/Next.js.md",
                "linksCollapsed": false,
                "unlinkedCollapsed": true
              }
            }
          },
          {
            "id": "32bac9fed2c3152d",
            "type": "leaf",
            "state": {
              "type": "backlink",
              "state": {
                "file": "프로그래밍언어/Next.js.md",
                "collapseAll": false,
                "extraContext": false,
                "sortOrder": "alphabetical",
                "showSearch": false,
                "searchQuery": "",
                "backlinkCollapsed": false,
                "unlinkedCollapsed": true
              }
            }
          },
          {
            "id": "645b06813e08ec73",
            "type": "leaf",
            "state": {
              "type": "advanced-tables-toolbar",
              "state": {}
            }
          }
        ]
      }
    ],
    "direction": "horizontal",
    "width": 246.5,
    "collapsed": true
  },
  "left-ribbon": {
    "hiddenItems": {
      "graph:그래프 뷰 열기": false,
      "templates:템플릿 삽입": false,
      "table-editor-obsidian:Advanced Tables Toolbar": false,
      "smart-random-note:Open Random Note from Search": false,
      "obsidian-excalidraw-plugin:Create new drawing": false
    }
  },
  "active": "4e715e4826be128a",
  "lastOpenFiles": [
    "프로그래밍언어/React.js.md",
    "프로그래밍언어/Next.js.md",
    "프로그래밍언어/JavaScript(JS).md",
    "프로그래밍언어/고급 프로그래밍 언어.md",
    "프로그래밍언어/객체 지향 프로그래밍 언어.md",
    "프로그래밍언어/기계어.md",
    "프로그래밍언어/어셈블리 언어(Assembly Language).md",
    "프로그래밍언어/프로그래밍 언어.md",
    "프로그래밍언어/C++.md",
    "프로그래밍언어/C.md",
    "프로그래밍언어/ALGOL.md",
    "프로그래밍언어/저급 프로그래밍 언어.md",
    "운영체제/Shared-Memory System.md",
    "운영체제/IPC (InterProcess Communication).md",
    "운영체제/Message-Passing System.md",
    "컴파일러/Lexical Analyzer(Scanner).md",
    "운영체제/RPC(Remote Procedure Calls).md",
    "운영체제/Indirect Communication.md",
    "정보보호/Substitution-Permutation(S-P) networks.md",
    "정보보호/Block Cipher Symmetric Encryption.md",
    "정보보호/Symmetric encryption.md",
    "정보보호/Vigenere Cipher.md",
    "정보보호/Block Cipher.md",
    "README.md",
    "컴파일러/컴파일러(Compiler).md",
    "정보보호/Feistel Cipher.md",
    "Untitled.canvas",
    "Context/spacesLastSync.log",
    "Context",
    "정보보호/Pasted image 20231012193806.png",
    "정보보호/Pasted image 20231012193746.png",
    "정보보호/Pasted image 20231012191353.png",
    "데이터베이스/Pasted image 20231012092230.png",
    "정보보호/Pasted image 20231011204140.png",
    "정보보호/Pasted image 20231006155252.png",
    "정보보호/Pasted image 20231006162737.png",
    "정보보호/Pasted image 20231006164233.png",
    "정보보호/Pasted image 20231005180415.png",
    "정보보호/Pasted image 20231005172837.png",
    "MixPath",
    "무제 파일.canvas",
    "Synchronous I",
    "I",
    "프로그래밍언어",
    "컴퓨터네트워크",
    "정보보호",
    "자료구조",
    "운영체제"
  ]
}